{
  "folder": "k9frJVrXOYBhXYbo",
  "name": "Bounty Hunter",
  "type": "ability",
  "_id": "udpwtP2JQ3ZQRLyx",
  "img": "systems/wfrp3e/assets/images/careers/bounty_hunter.webp",
  "system": {
    "description": "<p>Once per session, you may name one adversary as your quarry. Add [[DE]] to all Observation, Intuition, Melee Attack and Ranged Attack checks targeting your quarry for the remainder of the encounter</p>"
  },
  "effects": [],
  "sort": 0,
  "ownership": {
    "default": 0
  },
  "flags": {},
  "_stats": {
    "systemId": "wfrp3e",
    "systemVersion": "1.2",
    "coreVersion": "12.331",
    "createdTime": 1710869349804,
    "modifiedTime": 1710871093130,
    "lastModifiedBy": "Bq3CTOvANoOneedB",
    "compendiumSource": null,
    "duplicateSource": null
  },
  "_key": "!items!udpwtP2JQ3ZQRLyx"
}
