{
  "folder": "VUMz1tBRkXXXUVEt",
  "name": "Mangled Limb (SR: 3)",
  "type": "criticalWound",
  "img": "icons/svg/item-bag.svg",
  "system": {
    "description": "<p>Your Strength and Agility are reduced by 1. The damaged limb (GM&rsquo;s choice) does not function properly until this critical wound is healed. Add <span style=\"color: purple; -webkit-text-stroke: 1pt black;\">⧫</span> to all checks requiring use of the limb.</p>",
    "severityRating": 3
  },
  "effects": [],
  "sort": 0,
  "ownership": {
    "default": 0,
    "Bq3CTOvANoOneedB": 3
  },
  "flags": {
    "scene-packer": {
      "hash": "e887f8588ea8d82e103dff216364512fd95f67dc"
    }
  },
  "_stats": {
    "systemId": "wfrp3e",
    "systemVersion": "1.0.1-alpha",
    "coreVersion": "13.341",
    "createdTime": 1682264544162,
    "modifiedTime": 1715380997987,
    "lastModifiedBy": "Bq3CTOvANoOneedB",
    "compendiumSource": null,
    "duplicateSource": null,
    "exportSource": null
  },
  "_id": "E3JStQHoB3XQHFlK",
  "_key": "!items!E3JStQHoB3XQHFlK"
}
