{
  "folder": "VUMz1tBRkXXXUVEt",
  "name": "Minor Trauma (Agility)",
  "type": "criticalWound",
  "img": "icons/skills/wounds/anatomy-organ-heart-red.webp",
  "system": {
    "description": "<p>Add {Dm} to Agility checks.</p>",
    "severityRating": 3
  },
  "effects": [
    {
      "name": "Minor Trauma (Agility)",
      "img": "icons/skills/wounds/anatomy-organ-heart-red.webp",
      "_id": "C57CQQZcpVuCT0PC",
      "type": "base",
      "system": {
        "macro": {
          "priority": 0,
          "type": "checkPreparation",
          "script": "if(checkData.characteristic === \"agility\")\n  diePool.dice.misfortune++;"
        }
      },
      "changes": [],
      "disabled": false,
      "duration": {
        "startTime": null,
        "combat": null,
        "seconds": null,
        "rounds": null,
        "turns": null,
        "startRound": null,
        "startTurn": null
      },
      "description": "<p>Add {Dm} to Agility checks.</p>",
      "origin": null,
      "tint": "#ffffff",
      "transfer": true,
      "statuses": [],
      "sort": 0,
      "flags": {},
      "_key": "!items.effects!U6Z0LScLGU8N4llf.C57CQQZcpVuCT0PC"
    }
  ],
  "sort": 0,
  "ownership": {
    "default": 0
  },
  "flags": {},
  "_id": "U6Z0LScLGU8N4llf",
  "_key": "!items!U6Z0LScLGU8N4llf"
}
